modulus/sym/__init__.py
modulus/sym/constants.py
modulus/sym/graph.py
modulus/sym/key.py
modulus/sym/manager.py
modulus/sym/node.py
modulus/sym/trainer.py
modulus/sym/dataset/__init__.py
modulus/sym/dataset/continuous.py
modulus/sym/dataset/dataset.py
modulus/sym/dataset/discrete.py
modulus/sym/distributed/__init__.py
modulus/sym/distributed/helpers.py
modulus/sym/distributed/manager.py
modulus/sym/domain/__init__.py
modulus/sym/domain/domain.py
modulus/sym/domain/constraint/__init__.py
modulus/sym/domain/constraint/constraint.py
modulus/sym/domain/constraint/continuous.py
modulus/sym/domain/constraint/discrete.py
modulus/sym/domain/constraint/utils.py
modulus/sym/domain/inferencer/__init__.py
modulus/sym/domain/inferencer/inferencer.py
modulus/sym/domain/inferencer/ov.py
modulus/sym/domain/inferencer/pointwise.py
modulus/sym/domain/inferencer/voxel.py
modulus/sym/domain/inferencer/vtkpointwise.py
modulus/sym/domain/monitor/__init__.py
modulus/sym/domain/monitor/monitor.py
modulus/sym/domain/monitor/pointwise.py
modulus/sym/domain/validator/__init__.py
modulus/sym/domain/validator/continuous.py
modulus/sym/domain/validator/discrete.py
modulus/sym/domain/validator/validator.py
modulus/sym/eq/__init__.py
modulus/sym/eq/derivatives.py
modulus/sym/eq/non_dim.py
modulus/sym/eq/pde.py
modulus/sym/eq/mfd/__init__.py
modulus/sym/eq/mfd/finite_derivatives.py
modulus/sym/eq/mfd/functions.py
modulus/sym/eq/pdes/__init__.py
modulus/sym/eq/pdes/advection_diffusion.py
modulus/sym/eq/pdes/basic.py
modulus/sym/eq/pdes/diffusion.py
modulus/sym/eq/pdes/electromagnetic.py
modulus/sym/eq/pdes/energy_equation.py
modulus/sym/eq/pdes/linear_elasticity.py
modulus/sym/eq/pdes/navier_stokes.py
modulus/sym/eq/pdes/signed_distance_function.py
modulus/sym/eq/pdes/turbulence_zero_eq.py
modulus/sym/eq/pdes/wave_equation.py
modulus/sym/geometry/__init__.py
modulus/sym/geometry/adf.py
modulus/sym/geometry/curve.py
modulus/sym/geometry/discrete_geometry.py
modulus/sym/geometry/geometry.py
nvidia_modulus.sym-1.6.0.dist-info/LICENSE.txt
nvidia_modulus.sym-1.6.0.dist-info/METADATA
nvidia_modulus.sym-1.6.0.dist-info/WHEEL
nvidia_modulus.sym-1.6.0.dist-info/top_level.txt
nvidia_modulus.sym-1.6.0.dist-info/RECORD
