Metadata-Version: 2.1
Name: nvidia-modulus.sym
Version: 1.6.0
Summary: A deep learning framework for AI-driven multi-physics systems
Author: NVIDIA Modulus Team
License: Apache 2.0
Classifier: Programming Language :: Python :: 3
Classifier: License :: OSI Approved :: Apache Software License
Classifier: Operating System :: OS Independent
Requires-Python: >=3.10
License-File: LICENSE.txt
Requires-Dist: nvidia-modulus >=0.2.0
Requires-Dist: hydra-core >=1.2.0
Requires-Dist: termcolor >=2.1.1
Requires-Dist: chaospy >=4.3.7
Requires-Dist: Cython ==0.29.28
Requires-Dist: numpy-stl ==2.16.3
Requires-Dist: opencv-python ==4.9.0.80
Requires-Dist: scikit-learn >=1.2.0
Requires-Dist: symengine >=0.10.0
Requires-Dist: sympy ==1.12
Requires-Dist: timm >=1.0.3
Requires-Dist: torch-optimizer ==0.3.0
Requires-Dist: transforms3d ==0.3.1
Requires-Dist: typing ==3.7.4.3
Requires-Dist: pillow ==10.2.0
Requires-Dist: notebook ==6.4.12
Requires-Dist: mistune ==2.0.3
Requires-Dist: pint ==0.19.2
Requires-Dist: tensorboard >=2.8.0
Requires-Dist: vtk >=9.2.6
Requires-Dist: h5py >=3.7.0
